db-stubs/__init__.pyi
db-stubs/buffers/__init__.pyi
db-stubs/util/__init__.pyi
decompiler-stubs/__init__.pyi
docking-stubs/__init__.pyi
docking-stubs/action/__init__.pyi
docking-stubs/action/builder/__init__.pyi
docking-stubs/actions/__init__.pyi
docking-stubs/actions/dialog/__init__.pyi
docking-stubs/dnd/__init__.pyi
docking-stubs/event/__init__.pyi
docking-stubs/event/mouse/__init__.pyi
docking-stubs/framework/__init__.pyi
docking-stubs/help/__init__.pyi
docking-stubs/menu/__init__.pyi
docking-stubs/menu/keys/__init__.pyi
docking-stubs/options/__init__.pyi
docking-stubs/options/editor/__init__.pyi
docking-stubs/resources/__init__.pyi
docking-stubs/resources/icons/__init__.pyi
docking-stubs/test/__init__.pyi
docking-stubs/theme/__init__.pyi
docking-stubs/theme/gui/__init__.pyi
docking-stubs/tool/__init__.pyi
docking-stubs/tool/util/__init__.pyi
docking-stubs/util/__init__.pyi
docking-stubs/util/image/__init__.pyi
docking-stubs/widgets/__init__.pyi
docking-stubs/widgets/autocomplete/__init__.pyi
docking-stubs/widgets/button/__init__.pyi
docking-stubs/widgets/checkbox/__init__.pyi
docking-stubs/widgets/combobox/__init__.pyi
docking-stubs/widgets/conditiontestpanel/__init__.pyi
docking-stubs/widgets/dialogs/__init__.pyi
docking-stubs/widgets/fieldpanel/__init__.pyi
docking-stubs/widgets/fieldpanel/field/__init__.pyi
docking-stubs/widgets/fieldpanel/internal/__init__.pyi
docking-stubs/widgets/fieldpanel/listener/__init__.pyi
docking-stubs/widgets/fieldpanel/support/__init__.pyi
docking-stubs/widgets/filechooser/__init__.pyi
docking-stubs/widgets/filter/__init__.pyi
docking-stubs/widgets/imagepanel/__init__.pyi
docking-stubs/widgets/imagepanel/actions/__init__.pyi
docking-stubs/widgets/indexedscrollpane/__init__.pyi
docking-stubs/widgets/label/__init__.pyi
docking-stubs/widgets/list/__init__.pyi
docking-stubs/widgets/model/__init__.pyi
docking-stubs/widgets/numberformat/__init__.pyi
docking-stubs/widgets/pathmanager/__init__.pyi
ghidra_stubs-12.0.1.dist-info/licenses/LICENSE
ghidra_stubs-12.0.1.dist-info/METADATA
ghidra_stubs-12.0.1.dist-info/WHEEL
ghidra_stubs-12.0.1.dist-info/top_level.txt
ghidra_stubs-12.0.1.dist-info/RECORD
