Metadata-Version: 2.4
Name: ghidra-stubs
Version: 12.0.1
Summary: Ghidra Type Stubs
Maintainer: Ghidra Development Team
License: Apache-2.0
Keywords: ghidra
Classifier: License :: OSI Approved :: Apache Software License
Classifier: Typing :: Stubs Only
License-File: LICENSE
Dynamic: license-file
